iotile_support_prod_pod1m_1/CalibratePOD1MStep.py
iotile_support_prod_pod1m_1/ResetPOD1MStep.py
iotile_support_prod_pod1m_1/__init__.py
iotile_support_prod_pod1m_1/pod_1m.py
iotile_support_prod_pod1m_1/tracker_app.py
iotile_support_prod_pod1m_1-1.3.2.dist-info/METADATA
iotile_support_prod_pod1m_1-1.3.2.dist-info/WHEEL
iotile_support_prod_pod1m_1-1.3.2.dist-info/entry_points.txt
iotile_support_prod_pod1m_1-1.3.2.dist-info/top_level.txt
iotile_support_prod_pod1m_1-1.3.2.dist-info/RECORD
