Metadata-Version: 2.1
Name: iotile-support-prod-pod1m-1
Version: 1.3.2
Summary: UNKNOWN
Home-page: UNKNOWN
Author: Arch
Author-email: info@arch-iot.com
License: UNKNOWN
Platform: UNKNOWN
Requires-Dist: numpy (>=1.15.1)
Requires-Dist: sortedcontainers (~=2.1)
Requires-Dist: iotile-core (~=5.0)
Requires-Dist: iotile-ext-cloud (~=1.0)
Requires-Dist: iotile-sensorgraph (~=1.0)
